{
  "slug": "co-ed-frenzy",
  "title": "Co-ed Frenzy",
  "featuredTitle": "Co-ed Frenzy",
  "description": "A serial killer terrorizes university students in their co-ed dormitories.",
  "parent": "Blow Out",
  "parentYear": "1981",
  "rating": "R",
  "runtime": "2h 12m",
  "labels": [ "horror", "slasher" ],
  "credit": "Filmways Pictures",
  "altHero": "a young woman in the shower and the sillouhette of a knife",
  "alt1": "a cop peers into a window and a knife is pulled behind him",
  "alt2": "looking into a window where young women are dancing",
  "alt3": "peering around a corner at two women walking down a hallway",
  "alt4": "a steamy bathroom with the reflection of the killer in the mirror",
  "layout": "movie.pug",
  "stills": true,
  "tags": [
    "entry",
    "movie",
    "slasher flicks"
  ]
}
