{
  "slug": "courage-of-the-cosmos",
  "title": "Courage of the Cosmos",
  "featuredTitle": "Courage of the Cosmos",
  "description": "Major Courage and his crew protect the cosmos from Scumazoids, overlords, and others who do harm!",
  "quote": "We’re hopelessly outnumbered by the Scumazoids!",
  "parent": "DuckTales",
  "parentYear": "1987-1990",
  "rating": "TV-G",
  "runtime": "2h 4m",
  "starring": "Major Courage",
  "studio": "Duckburg Studios",
  "labels": "sci-fi, adventure",
  "credit": "Buena Vista Television",
  "layout": "movie.pug",
  "stills": true,
  "tags": [
    "entry",
    "tv series",
    "sci-fi tv"
  ]
}
