{
  "slug": "its-smoochy-time",
  "title": "It’s Smoochy Time",
  "featuredTitle": "It’s Smoochy Time",
  "description": "Welcome to Smoochy’s Magic Jungle! Join the Rhinettes and do the Jiggy Ziggy dance and peek inside the Magic Cookie Bag.",
  "quote": "Wasn’t that fun in an awkward sort of way?",
  "parent": "Death to Smoochy",
  "parentYear": "2002",
  "rating": "TV-Y",
  "runtime": "2 seasons",
  "starring": [ "Sheldon Mopes" ],
  "studio": "Kidnet Television",
  "labels": [ "kids", "variety" ],
  "credit": "Warner Bros. Pictures",
  "altHero": "Smoochy the Rhino",
  "alt1": "Smoochy cheering with a bunch of kids",
  "alt2": "Smoochy and kids about to look in the Magic Cookie Bag",
  "alt3": "Smoochy holding a penis-shaped cookie",
  "alt4": "Smoochy playing guitar and singing with the Rhinettes",
  "layout": "movie.pug",
  "stills": true,
  "tags": [
    "entry",
    "tv series",
    "kids variety shows"
  ]
}
