{
  "slug": "lemony-lick-its-a-series-of-horny-events",
  "title": "Lemony Lick-It’s A Series of Horny Events",
  "featuredTitle": "Lemony Lick-It’s A Series of Horny Events",
  "description": "The cast of <em>Fahrenheit 9 on 1</em> reunites for this science fiction snuggle film.",
  "quote": "We’ve been on this space ship for 100 years. When will we ever get to Planet Satisfaction?",
  "parent": "The Simpsons",
  "parentYear": "1989-Present",
  "rating": "Unrated",
  "runtime": "43m",
  "starring": "Angela Dare, Sultry Stevens",
  "studio": "Gentlemen's Relief Productions",
  "labels": [ "adult", "sci-fi" ],
  "credit": "20th Television",
  "altHero": "two sexy women in space costumes sit on the Simpsons’ family room couch",
  "layout": "movie.pug",
  "tags": [
    "entry",
    "movie",
    "adults 18+"
  ]
}
