{
  "slug": "les-cousins-dangereux",
  "title": "Les Cousins Dangereux",
  "description": "A French film centers around a budding but forbidden romance between two cousins. A ‘relative’ masterpiece of complex eroticism.",
  "quote": "Aimerais-tu jouer?",
  "parent": "Arrested Development",
  "parentYear": "2003-2006",
  "parentIMDB": "0367279",
  "rating": "R",
  "runtime": "1h 47m",
  "director": [
    "Francois Sauterne",
    "Gerard Sauterne"
  ],
  "labels": [
    "romantic drama"
  ],
  "credit": "20th Television, Netflix",
  "altHero": "a teen boy gazes at his female cousin",
  "layout": "movie.pug",
  "tags": [
    "entry",
    "movie",
    "romantic dramas"
  ]
}
