{
  "slug": "the-krusty-the-clown-show",
  "title": "The Krusty the Clown Show",
  "description": "Krusty the Clown hosts his long-running variety kids show featuring physical jokes, comedy sketches, and special guests.",
  "quote": "Hey, Hey Kids!",
  "parent": "The Simpsons",
  "parentYear": "1989-Present",
  "parentIMDB": "0096697",
  "rating": "TV-Y7",
  "runtime": "60 seasons",
  "starring": [
    "Krusty the Clown",
    "Mr. Teeny",
    "Sideshow Mel",
    "Tina Ballerina",
    "Sideshow Raheem",
    "Sideshow Bob",
    "Sideshow Cassandra"
  ],
  "studio": "Channel 6, HBOWTIME",
  "labels": [
    "kids",
    "variety shows"
  ],
  "credit": "20th Television",
  "altHero": "Krusty the Clown laughing",
  "alt1": "Krusty driving a litle circus car",
  "alt2": "Side Show Bob passionately reading a book",
  "alt3": "Krusty and Side Show Mel playing his slide whistle",
  "alt4": "Krusty smiling wide and holding an axe",
  "layout": "movie.pug",
  "stills": true,
  "tags": [
    "entry",
    "TV series",
    "kids variety shows"
  ]
}
