{
  "slug": "the-pride-of-plymouth-rock",
  "title": "The Pride of Plymouth Rock",
  "featuredTitle": "The Pride of Plymouth Rock",
  "description": "The story of two Mayflower Pilgrims and their life in Plymouth Colony. One film every patriotic American has been waiting for.",
  "quote": "Gaze upon this bountiful and beauteous place.",
  "parent": "For Your Consideration",
  "parentYear": "2006",
  "rating": "PG-13",
  "runtime": "2h 33m",
  "starring": "Jim Beyman, Cynthia Chapman",
  "labels": "drama, history",
  "credit": "Warner Independent Pictures",
  "altHero": "two Pilgrims, a man and a woman, talk with the ocean in the background",
  "alt1": "a wider shot of the Pilgrims on a snowy beach, their boat nearby",
  "alt2": "the Pilgrims",
  "alt3": "closeup of the woman",
  "alt4": "closeup of the man",
  "layout": "movie.pug",
  "stills": true,
  "tags": [
    "entry",
    "movie",
    "war and historical dramas"
  ]
}
