{
  "slug": "the-passion-of-the-christ-2-crucify-this",
  "title": "The Passion of the Christ 2: Crucify This",
  "featuredTitle": "The Passion of the Christ 2: Crucify This",
  "description": "The follow-up to <em>The Passion of the Christ</em>. Let he who is without sin, kick the first ass.",
  "quote": "For the son of God, you sure are a son of a… whoooaa!",
  "parent": "Family Guy",
  "parentYear": "1999-Present",
  "rating": "R",
  "runtime": "2h 22m",
  "starring": [
    "Chris Tucker",
    "Jim Caviziel"
  ],
  "director": [
    "Mel Gibson"
  ],
  "labels": [
    "action comedy",
    "religion",
    "high-speed chases"
  ],
  "credit": "20th Television",
  "altHero": "Jesus driving a convertible with Chris Tucker in shotgun",
  "alt1": "the convertible makes a big jump in front of an explosion",
  "alt2": "Jesus in action, wielding two guns",
  "alt3": "Chris Tucker offers Jesus a blunt",
  "alt4": "Tucker and Jesus blown through the air from an explosion",
  "layout": "movie.pug",
  "stills": true,
  "tags": [
    "entry",
    "movie",
    "action movies"
  ]
}
