{
  "slug": "where-theres-a-will-theres-a-way",
  "title": "Where There’s a Will There’s a Way",
  "description": "A cheerful romp about an independent woman in post-war Hollywood.",
  "parent": "Enemy",
  "parentYear": "2013",
  "rating": "PG",
  "runtime": "1h 36m",
  "starring": [
    "Ellen Lipton",
    "Tara Wexler",
    "Caley Grodin",
    "Josh Channing",
    "Matt Singleton"
  ],
  "director": [
    "Ellen Lipton"
  ],
  "labels": [
    "comedy"
  ],
  "credit": "Entertainment One",
  "altHero": "Lipton in fancy dress and sunglasses screams in delight",
  "alt1": "Lipton at the reception desk at a vintage hotel",
  "alt2": "a bellhop smiling",
  "alt3": "a man leans over to speak to a woman who is distractedly looking off screen",
  "alt4": "Lipton talks with a man while a bellhop holds her luggage",
  "layout": "movie.pug",
  "stills": true,
  "tags": [
    "entry",
    "movie",
    "comedies"
  ]
}
